get_my_pastebin.py
get_my_pastebin-1.0.12.dist-info/DESCRIPTION.rst
get_my_pastebin-1.0.12.dist-info/METADATA
get_my_pastebin-1.0.12.dist-info/RECORD
get_my_pastebin-1.0.12.dist-info/WHEEL
get_my_pastebin-1.0.12.dist-info/entry_points.txt
get_my_pastebin-1.0.12.dist-info/metadata.json
get_my_pastebin-1.0.12.dist-info/top_level.txt
